{"hash":"1acd9ff7544f5ebc679a6336555ee451878b9c4a","data":{"post":{"title":"Organizing Everyone Plays the Same Song","description":"Google Forms + Google Sheets for the win","path":"/blog/organizing-everyone-plays-the-same-song/","content":"<p>I put together everyoneplaysthesamesong as an excuse to engage in something with friends remotely, and to use social pressure to force me/us to practice music. </p>\n<p>Thanks for Google Forms and Google Sheets, the organization effort was quite simple. </p>\n<p>I used two Forms to get information from participants - </p>\n<ul>\n<li>The signup / cover song submission form</li>\n<li>The post-submission voting form</li>\n</ul>\n<p>I'm not going to get into setting up a Form itself, because it's very straightforward. What I DO want to call out some Google Forms best practices and the Google Sheets integration that's a few clicks away. </p>\n<h3 id=\"google-forms-best-practices\"><a href=\"#google-forms-best-practices\" aria-hidden=\"true\"><span class=\"icon icon-link\"></span></a>Google Forms best practices</h3>\n<ul>\n<li>If you need to respond or send results to the people submitting for the form, make sure to include a mandatory contact information field, be in email, phone number, etc. </li>\n<li>Each form field will get its own column in google sheets, so be mindful of how your data will be organized once participants have submitted their data.</li>\n</ul>\n<h3 id=\"google-forms--google-sheets-integration\"><a href=\"#google-forms--google-sheets-integration\" aria-hidden=\"true\"><span class=\"icon icon-link\"></span></a>Google Forms + Google Sheets Integration</h3>\n<img src=\"/uploads/5googleformssheetsintegrationlink.png\" width=\"600\">\n","date":"2020-05-04T01:45:28.838Z"}},"context":{}}